dailyscheduler/__init__.py
dailyscheduler/abstract_classes.py
dailyscheduler/classes.py
test/__init__.py
test/test_task.py
test/test_workingday.py
dailyscheduler-0.0.4.dist-info/LICENSE
dailyscheduler-0.0.4.dist-info/METADATA
dailyscheduler-0.0.4.dist-info/WHEEL
dailyscheduler-0.0.4.dist-info/top_level.txt
dailyscheduler-0.0.4.dist-info/RECORD
