Metadata-Version: 2.1
Name: dailyscheduler
Version: 0.0.4
Summary: Schedule tasks troughout the day.
Author: NumenMirus
Author-email: <numenmirus@proton.me>
Keywords: day,scheduler,tasks,schedule,time
Classifier: Development Status :: 1 - Planning
Classifier: Intended Audience :: Developers
Classifier: Programming Language :: Python :: 3
Classifier: Operating System :: Unix
Classifier: Operating System :: MacOS :: MacOS X
Classifier: Operating System :: Microsoft :: Windows
License-File: LICENSE
